easy_cloudrun/__init__.py
easy_cloudrun/utils.py
easy_cloudrun-1.0.1.dist-info/LICENSE
easy_cloudrun-1.0.1.dist-info/METADATA
easy_cloudrun-1.0.1.dist-info/WHEEL
easy_cloudrun-1.0.1.dist-info/top_level.txt
easy_cloudrun-1.0.1.dist-info/RECORD
