Metadata-Version: 2.1
Name: easy-cloudrun
Version: 1.0.1
Summary: GCP Cloud Run 을 사용 할 때 테스트, 빌드, 배포, GCP 이미지 삭제 등을 간단하게 해주는 패키지입니다.
Home-page: https://github.com/da-huin/easy_cloudrun
Author: JunYeong Park
Author-email: dahuin000@gmail.com
License: MIT
Download-URL: https://github.com/da-huin/easy_cloudrun/archive/master.zip
Platform: UNKNOWN
Classifier: Programming Language :: Python :: 3
Requires-Dist: pyyaml
